engine/__init__.py
Mits_Engine-1.0.10.dist-info/METADATA
Mits_Engine-1.0.10.dist-info/WHEEL
Mits_Engine-1.0.10.dist-info/entry_points.txt
Mits_Engine-1.0.10.dist-info/top_level.txt
Mits_Engine-1.0.10.dist-info/RECORD
